yagura/__init__.py
yagura/cli.py
yagura/urls.py
yagura/utils.py
yagura/wsgi.py
yagura/accounts/__init__.py
yagura/accounts/admin.py
yagura/accounts/apps.py
yagura/accounts/forms.py
yagura/accounts/middleware.py
yagura/accounts/models.py
yagura/accounts/tests.py
yagura/accounts/urls.py
yagura/accounts/views.py
yagura/accounts/fixtures/unittest_suite.json
yagura/accounts/locale/ja/LC_MESSAGES/django.mo
yagura/accounts/locale/ja/LC_MESSAGES/django.po
yagura/accounts/migrations/0001_initial.py
yagura/accounts/migrations/__init__.py
yagura/accounts/templates/accounts/profile.html
yagura/accounts/templates/accounts/profile_edit.html
yagura/accounts/templates/accounts/social_error.html
yagura/accounts/templates/django_registration/activation_complete.html
yagura/accounts/templates/django_registration/activation_email_body.txt
yagura/accounts/templates/django_registration/activation_email_subject.txt
yagura/accounts/templates/django_registration/activation_failed.html
yagura/accounts/templates/django_registration/registration_complete.html
yagura/accounts/templates/django_registration/registration_form.html
yagura/accounts/templates/registration/logged_out.html
yagura/accounts/templates/registration/login.html
yagura/accounts/templates/registration/_snippets/social-auth.html
yagura/accounts/templatetags/__init__.py
yagura/accounts/templatetags/social_labels.py
yagura/core/__init__.py
yagura/core/admin.py
yagura/core/apps.py
yagura/core/context_processors.py
yagura/core/models.py
yagura/core/tests.py
yagura/core/urls.py
yagura/core/views.py
yagura/core/locale/ja/LC_MESSAGES/django.mo
yagura/core/locale/ja/LC_MESSAGES/django.po
yagura/core/migrations/__init__.py
yagura/core/static/layout.css
yagura/core/templates/index.html
yagura/core/templates/layouts/base.html
yagura/core/templates/layouts/single_page.html
yagura/core/templates/layouts/two_pane.html
yagura/core/templates/layouts/two_pane_single.html
yagura/monitors/__init__.py
yagura/monitors/admin.py
yagura-0.12.0.dist-info/LICENSE
yagura-0.12.0.dist-info/METADATA
yagura-0.12.0.dist-info/WHEEL
yagura-0.12.0.dist-info/entry_points.txt
yagura-0.12.0.dist-info/top_level.txt
yagura-0.12.0.dist-info/RECORD
