Metadata-Version: 2.1
Name: yagura
Version: 0.12.0
Summary: Simple website monitoring kit
Home-page: https://gitlab.com/attakei/yagura
Author: attakei
Author-email: attakei@gmail.com
License: UNKNOWN
Platform: UNKNOWN
Classifier: Development Status :: 4 - Beta
Classifier: Intended Audience :: Developers
Classifier: License :: OSI Approved :: BSD License
Classifier: Programming Language :: Python :: 3.6
Classifier: Programming Language :: Python :: 3.7
Requires-Dist: Django (>=2.0)
Requires-Dist: django-bulma
Requires-Dist: django-registration (>=3.0)
Requires-Dist: django-templated-email
Requires-Dist: django-crontab
Requires-Dist: django-environ
Requires-Dist: pyasn1
Requires-Dist: social-auth-app-django
Requires-Dist: slackweb
Requires-Dist: aiohttp (<3.5.0)
Requires-Dist: requests
